zopyx/__init__.py
zopyx/checker.py
zopyx.check_ssl_domains-1.0.dist-info/METADATA
zopyx.check_ssl_domains-1.0.dist-info/WHEEL
zopyx.check_ssl_domains-1.0.dist-info/entry_points.txt
zopyx.check_ssl_domains-1.0.dist-info/top_level.txt
zopyx.check_ssl_domains-1.0.dist-info/RECORD
